petk/__init__.py
petk/constants.py
petk/explore.py
petk/privacy.py
petk/tools.py
petk-0.0.2.dist-info/LICENSE
petk-0.0.2.dist-info/METADATA
petk-0.0.2.dist-info/WHEEL
petk-0.0.2.dist-info/top_level.txt
petk-0.0.2.dist-info/RECORD
