Metadata-Version: 2.1
Name: petk
Version: 0.0.2
Summary: A toolkit to assist data exploration for both tabular and geospatial data
Home-page: https://github.com/open-data-toronto/petk
Author: Open Data Toronto
Author-email: opendata@toronto.ca
License: MIT
Platform: UNKNOWN
Classifier: Development Status :: 4 - Beta
Classifier: Environment :: Console
Classifier: Framework :: IPython
Classifier: Intended Audience :: Developers
Classifier: Intended Audience :: Science/Research
Classifier: License :: OSI Approved :: MIT License
Classifier: Operating System :: OS Independent
Classifier: Programming Language :: Python :: 3
Classifier: Topic :: Scientific/Engineering
Requires-Dist: geopandas (>=0.4.0)
